fintorch/__init__.py
fintorch/cli.py
fintorch/fintorch.py
fintorch/datasets/README.md
fintorch/datasets/__init__.py
fintorch/datasets/airpassenger.py
fintorch/datasets/auctiondata.py
fintorch/datasets/electricity_simple.py
fintorch/datasets/elliptic.py
fintorch/datasets/ellipticpp.py
fintorch/datasets/invoice.py
fintorch/datasets/marketdata.py
fintorch/datasets/stockticker.py
fintorch/datasets/synthetic/__init__.py
fintorch/datasets/synthetic/simpleSynthetic.py
fintorch/graph/__init__.py
fintorch/graph/layers/__init__.py
fintorch/graph/layers/beanconv.py
fintorch/layers/__init__.py
fintorch/models/__init__.py
fintorch/models/dl/__init__.py
fintorch/models/graph/__init__.py
fintorch/models/graph/graphbean/GraphBEANModule.yaml
fintorch/models/graph/graphbean/__init__.py
fintorch/models/graph/graphbean/graphBEAN.py
fintorch/models/graph/graphbean/wand/__init__.py
fintorch/models/graph/graphbean/wand/sweep.py
fintorch/models/timeseries/tft/GatedResidualNetwork.py
fintorch/models/timeseries/tft/InterpretableMultiHeadAttention.py
fintorch/models/timeseries/tft/VariableSelectionNetwork.py
fintorch/models/timeseries/tft/__init__.py
fintorch/models/timeseries/tft/tft.py
fintorch/models/timeseries/tft/tft_module.py
fintorch/models/timeseries/tft/utils.py
fintorch/utils/README.md
fintorch-0.6.0.dist-info/METADATA
fintorch-0.6.0.dist-info/WHEEL
fintorch-0.6.0.dist-info/entry_points.txt
fintorch-0.6.0.dist-info/licenses/LICENSE
fintorch-0.6.0.dist-info/RECORD
