Metadata-Version: 2.4
Name: fintorch
Version: 0.6.0
Summary: AI4FinTech project  repository
Project-URL: Homepage, https://github.com/AI4FinTech/fintorch
Author-email: Marcel Boersma <boersma.marcel@gmail.com>
License: MIT License
License-File: LICENSE
Keywords: fintorch
Classifier: Development Status :: 2 - Pre-Alpha
Classifier: Intended Audience :: Developers
Classifier: License :: OSI Approved :: MIT License
Classifier: Natural Language :: English
Classifier: Programming Language :: Python :: 3.10
Requires-Python: >=3.10
Requires-Dist: click>=7.0
Requires-Dist: entmax
Requires-Dist: huggingface-hub
Requires-Dist: kaggle==1.6.14
Requires-Dist: lightning
Requires-Dist: networkx
Requires-Dist: neuralforecast>=1.7.6
Requires-Dist: numpy<2
Requires-Dist: optuna
Requires-Dist: optuna-integration
Requires-Dist: pillow
Requires-Dist: polars>=1.14
Requires-Dist: ray[tune]==2.10
Requires-Dist: seaborn
Requires-Dist: tenacity
Requires-Dist: torch
Requires-Dist: torch-geometric
Requires-Dist: torchvision
Requires-Dist: wandb>=0.12.1
Requires-Dist: yfinance
Provides-Extra: dev
Requires-Dist: black==24.3.0; extra == 'dev'
Requires-Dist: bump-my-version; extra == 'dev'
Requires-Dist: coverage==4.5.4; extra == 'dev'
Requires-Dist: flake8==3.7.8; extra == 'dev'
Requires-Dist: jinja2; extra == 'dev'
Requires-Dist: mypy; extra == 'dev'
Requires-Dist: nbsphinx==0.8.6; extra == 'dev'
Requires-Dist: pandas-stubs; extra == 'dev'
Requires-Dist: pandoc; extra == 'dev'
Requires-Dist: pip-tools; extra == 'dev'
Requires-Dist: pip==23.3; extra == 'dev'
Requires-Dist: pre-commit; extra == 'dev'
Requires-Dist: pytest==6.2.4; extra == 'dev'
Requires-Dist: ruff; extra == 'dev'
Requires-Dist: sphinx-rtd-theme; extra == 'dev'
Requires-Dist: sphinx==4.1.2; extra == 'dev'
Requires-Dist: tox==3.14.0; extra == 'dev'
Requires-Dist: twine==1.14.0; extra == 'dev'
Requires-Dist: types-requests; extra == 'dev'
Requires-Dist: types-tqdm; extra == 'dev'
Requires-Dist: watchdog; extra == 'dev'
Requires-Dist: wheel==0.38.1; extra == 'dev'
